AUTHORS.txt
INSTALL.txt
LICENSE.txt
MANIFEST.in
README.txt
setup.cfg
setup.py
bin/woven-admin.py
docs/changelog.rst
docs/commands.rst
docs/conf.py
docs/conventions.rst
docs/index.rst
docs/main.rst
docs/settings.rst
docs/troubleshooting.rst
docs/tutorial.rst
docs/woven/deployment.rst
docs/woven/linux.rst
docs/woven/main.rst
docs/woven/project.rst
docs/woven/virtualenv.rst
docs/woven/webservers.rst
docs/woven/woven.rst
woven/__init__.py
woven/api.py
woven/decorators.py
woven/deploy.py
woven/deployment.py
woven/environment.py
woven/linux.py
woven/project.py
woven/virtualenv.py
woven/webservers.py
woven.egg-info/PKG-INFO
woven.egg-info/SOURCES.txt
woven.egg-info/dependency_links.txt
woven.egg-info/requires.txt
woven.egg-info/top_level.txt
woven/management/__init__.py
woven/management/base.py
woven/management/commands/__init__.py
woven/management/commands/activate.py
woven/management/commands/bundle.py
woven/management/commands/deploy.py
woven/management/commands/node.py
woven/management/commands/patch.py
woven/management/commands/setupnode.py
woven/management/commands/startsites.py
woven/templates/setup.py
woven/templates/distribution_template/setup.py
woven/templates/distribution_template/project_name/__init__.py
woven/templates/distribution_template/project_name/manage.py
woven/templates/distribution_template/project_name/settings.py
woven/templates/distribution_template/project_name/urls.py
woven/templates/woven/django-apache-template.txt
woven/templates/woven/django-wsgi-template.txt
woven/templates/woven/gunicorn.conf
woven/templates/woven/maintenance.html
woven/templates/woven/nginx-gunicorn-template.txt
woven/templates/woven/nginx-template.txt
woven/templates/woven/requirements.txt
woven/templates/woven/sitesettings.txt
woven/templates/woven/ufw.txt
woven/templates/woven/etc/apache2/ports.conf
woven/templates/woven/etc/init.d/nginx
woven/templates/woven/etc/nginx/nginx.conf
woven/templates/woven/etc/nginx/proxy.conf
woven/templates/woven/etc/nginx/sites-available/default
woven/templates/woven/etc/postgresql/8.4/main/pg_hba.conf
woven/templates/woven/etc/postgresql/8.4/main/postgresql.conf
