Metadata-Version: 1.0
Name: woven
Version: 0.8
Summary: A deployment tool for Django built on Fabric
Home-page: http://github.com/bretth/woven
Author: Brett Haydon
Author-email: brett@haydon.id.au
License: UNKNOWN
Download-URL: http://github.com/bretth/woven/downloads/
Platform: UNKNOWN
Classifier: Development Status :: 3 - Alpha
Classifier: Environment :: Web Environment
Classifier: Framework :: Django
Classifier: Intended Audience :: Developers
Classifier: License :: OSI Approved :: BSD License
Classifier: Operating System :: OS Independent
Classifier: Programming Language :: Python
Classifier: Topic :: Software Development :: Libraries :: Python Modules
Classifier: Topic :: Utilities
